[
    {
        "name": "Indian Coffee House",
        "cuisine": "South Indian, Chinese, Biryani, Seafood",
        "price_for_two": "₹200 for one",
        "location": "Opens at 7am",
        "page_link": [
            "https://www.zomato.com/thalassery/indian-coffee-house-2-thalassery-locality/order"
        ]
    },
    {
        "name": "Momo Box",
        "cuisine": "Chinese, Burger, Shake",
        "price_for_two": "₹150 for one",
        "location": "Opens at 12:45pm",
        "page_link": [
            "https://www.zomato.com/thalassery/momo-box-3-thalassery-locality/order"
        ]
    },
    {
        "name": "Shake Verse",
        "cuisine": "Fast Food, South Indian, North Indian",
        "price_for_two": "₹200 for one",
        "location": "Opens at 12:45pm",
        "page_link": [
            "https://www.zomato.com/thalassery/shake-verse-thalassery-locality/order"
        ]
    },
    {
        "name": "Thalassery Dum Biriyani",
        "cuisine": "Biryani",
        "price_for_two": "₹200 for one",
        "location": "Opens at 12:45pm",
        "page_link": [
            "https://www.zomato.com/thalassery/thalassery-dum-biriyani-thalassery-locality/order"
        ]
    }
]